iCompress/__init__.py
iCompress/__main__.py
iCompress/compress.py
iCompress/decompress.py
iCompress/services/__init__.py
iCompress/services/compression_core/__init__.py
iCompress/services/compression_core/encoding_and_decoding.py
iCompress/services/compression_core/frequency.py
iCompress/services/compression_core/frequency_tree.py
iCompress/services/compression_core/padding.py
iCompress/services/compression_core/prepare_dictionary.py
iCompress/services/file_service/__init__.py
iCompress/services/file_service/file_metadata.py
iCompress/services/file_service/file_write.py
icompress-0.1.2.dist-info/METADATA
icompress-0.1.2.dist-info/WHEEL
icompress-0.1.2.dist-info/top_level.txt
icompress-0.1.2.dist-info/RECORD
