Metadata-Version: 2.4
Name: iCompress
Version: 0.1.2
Summary: A Python package for text compression using huffman coding.
Home-page: https://github.com/rahulrathod315/iCompress-The-File-Compressor
Author: Rahul Rathod
Author-email: rahul.rathod@gmail.com
Classifier: Programming Language :: Python :: 3
Classifier: License :: OSI Approved :: MIT License
Classifier: Operating System :: OS Independent
Requires-Python: >=3.6
Dynamic: author
Dynamic: author-email
Dynamic: classifier
Dynamic: description
Dynamic: description-content-type
Dynamic: home-page
Dynamic: requires-python
Dynamic: summary
